{"stats":{"player_id":29,"player_name":"ГОЛЫЦИНА ЮЛИЯ","events_played":1,"games_played":6,"total_pins":10050,"average_score":167.5,"best_game":202,"worst_game":145,"score_diff":57,"strike_attempts":65,"strikes":15,"strike_percent":23.08,"spares":31,"opens":16,"spare_conversion_percent":65.96,"singles_left":19,"singles_converted":14,"singles_missed":5,"single_pin_percent":73.68},"games":[{"game_id":169,"game_number":1,"play_date":"2026-05-04","time_start":"12:19:00","time_end":"12:40:00","lane":20,"event":"doubles","total_score":202},{"game_id":170,"game_number":2,"play_date":"2026-05-04","time_start":"12:47:00","time_end":"13:14:00","lane":21,"event":"doubles","total_score":166},{"game_id":171,"game_number":3,"play_date":"2026-05-04","time_start":"13:15:00","time_end":"13:40:00","lane":24,"event":"doubles","total_score":160},{"game_id":172,"game_number":4,"play_date":"2026-05-04","time_start":"13:43:00","time_end":"14:07:00","lane":25,"event":"doubles","total_score":145},{"game_id":173,"game_number":5,"play_date":"2026-05-04","time_start":"14:09:00","time_end":"14:35:00","lane":28,"event":"doubles","total_score":152},{"game_id":174,"game_number":6,"play_date":"2026-05-04","time_start":"14:37:00","time_end":"15:00:00","lane":29,"event":"doubles","total_score":180}]}