{
  "1": {
    "name": "степин алексей",
    "gender": "М",
    "hand": "R"
  },
  "2": {
    "name": "аврамчик михаил",
    "gender": "М",
    "hand": "R"
  },
  "3": {
    "name": "криворучко роман",
    "gender": "М",
    "hand": "L"
  },
  "4": {
    "name": "миненко александр",
    "gender": "М",
    "hand": "R"
  },
  "5": {
    "name": "орлов илья",
    "gender": "М",
    "hand": "R"
  },
  "6": {
    "name": "ефимов андрей",
    "gender": "М",
    "hand": "R"
  },
  "7": {
    "name": "коломеец дмитрий",
    "gender": "М",
    "hand": "R"
  },
  "8": {
    "name": "челпанов дмитрий",
    "gender": "М",
    "hand": "R"
  },
  "9": {
    "name": "царенко степан",
    "gender": "М",
    "hand": "R"
  },
  "10": {
    "name": "леденев иван",
    "gender": "М",
    "hand": "R"
  },
  "11": {
    "name": "кузнецов никита",
    "gender": "М",
    "hand": "R"
  },
  "12": {
    "name": "вологин геннадий",
    "gender": "М",
    "hand": "R"
  },
  "13": {
    "name": "авилов виктор",
    "gender": "М",
    "hand": "R"
  },
  "14": {
    "name": "демьяшев александр",
    "gender": "М",
    "hand": "R"
  },
  "15": {
    "name": "куделя сергей",
    "gender": "М",
    "hand": "R"
  },
  "16": {
    "name": "галочкин алексей",
    "gender": "М",
    "hand": "R"
  },
  "17": {
    "name": "алимпиев дмитрий",
    "gender": "М",
    "hand": "R"
  },
  "18": {
    "name": "париц дина",
    "gender": "Ж",
    "hand": "R"
  },
  "19": {
    "name": "золотухин ярослав",
    "gender": "М",
    "hand": "R"
  },
  "20": {
    "name": "мухлынин александр",
    "gender": "М",
    "hand": "R"
  },
  "21": {
    "name": "шукаев максим",
    "gender": "М",
    "hand": "R"
  },
  "22": {
    "name": "дукшанин андрей",
    "gender": "М",
    "hand": "R"
  },
  "23": {
    "name": "батыгин сергей",
    "gender": "М",
    "hand": "R"
  },
  "24": {
    "name": "кормилицин дмитрий",
    "gender": "М",
    "hand": "L"
  },
  "25": {
    "name": "рошонок герман",
    "gender": "М",
    "hand": "R"
  },
  "26": {
    "name": "золотухин глеб",
    "gender": "М",
    "hand": "R"
  },
  "27": {
    "name": "белянин вячеслав",
    "gender": "М",
    "hand": "R"
  },
  "28": {
    "name": "хостегян ашот",
    "gender": "М",
    "hand": "R"
  },
  "29": {
    "name": "эккель руслан",
    "gender": "М",
    "hand": "R"
  },
  "30": {
    "name": "мищенков сергей",
    "gender": "М",
    "hand": "R"
  },
  "31": {
    "name": "бышенко кирилл",
    "gender": "М",
    "hand": "R"
  },
  "32": {
    "name": "еловикова екатерина",
    "gender": "Ж",
    "hand": "L"
  },
  "33": {
    "name": "копьев глеб",
    "gender": "М",
    "hand": "L"
  },
  "34": {
    "name": "сидоров андрей",
    "gender": "М",
    "hand": "R"
  },
  "35": {
    "name": "сазонова елена",
    "gender": "Ж",
    "hand": "R"
  },
  "36": {
    "name": "рогов сергей",
    "gender": "М",
    "hand": "R"
  },
  "37": {
    "name": "сверчков владимир",
    "gender": "М",
    "hand": "L"
  },
  "38": {
    "name": "кузнецов владимир",
    "gender": "М",
    "hand": "R"
  },
  "39": {
    "name": "щелкунов станислав",
    "gender": "М",
    "hand": "R"
  },
  "40": {
    "name": "баранов василий",
    "gender": "М",
    "hand": "R"
  },
  "41": {
    "name": "луговой геннадий",
    "gender": "М",
    "hand": "R"
  },
  "42": {
    "name": "кириллов иван",
    "gender": "М",
    "hand": "R"
  },
  "43": {
    "name": "федорова анастасия",
    "gender": "Ж",
    "hand": "R"
  },
  "44": {
    "name": "ермаков денис",
    "gender": "М",
    "hand": "R"
  },
  "45": {
    "name": "пашковский александр",
    "gender": "М",
    "hand": "R"
  },
  "46": {
    "name": "тилемисов аманжол",
    "gender": "М",
    "hand": "R"
  },
  "47": {
    "name": "скрипников дмитрий",
    "gender": "М",
    "hand": "R"
  },
  "48": {
    "name": "елисеев андрей",
    "gender": "М",
    "hand": "R"
  },
  "49": {
    "name": "парахневич андрей",
    "gender": "М",
    "hand": "R"
  },
  "50": {
    "name": "лавров евгений",
    "gender": "М",
    "hand": "R"
  },
  "51": {
    "name": "жабановский дмитрий",
    "gender": "М",
    "hand": "R"
  },
  "52": {
    "name": "смирнов станислав",
    "gender": "М",
    "hand": "R"
  },
  "53": {
    "name": "исхаков махмут",
    "gender": "М",
    "hand": "R"
  },
  "54": {
    "name": "михеенко станислав",
    "gender": "М",
    "hand": "R"
  },
  "55": {
    "name": "середенко иван",
    "gender": "М",
    "hand": "R"
  },
  "56": {
    "name": "сазонов юрий",
    "gender": "М",
    "hand": "R"
  },
  "57": {
    "name": "коряков вадим",
    "gender": "М",
    "hand": "R"
  },
  "58": {
    "name": "сусликов семен",
    "gender": "М",
    "hand": "R"
  },
  "59": {
    "name": "околелов иван",
    "gender": "М",
    "hand": "R"
  },
  "60": {
    "name": "гуляев евгений",
    "gender": "М",
    "hand": "R"
  },
  "61": {
    "name": "вещунов игорь",
    "gender": "М",
    "hand": "R"
  },
  "62": {
    "name": "абдуллин артур",
    "gender": "М",
    "hand": "R"
  },
  "63": {
    "name": "леванюк дмитрий",
    "gender": "М",
    "hand": "R"
  },
  "64": {
    "name": "бут андрей",
    "gender": "М",
    "hand": "R"
  },
  "65": {
    "name": "суслов андрей",
    "gender": "М",
    "hand": "R"
  },
  "66": {
    "name": "хавченко дмитрий",
    "gender": "М",
    "hand": "R"
  },
  "67": {
    "name": "гребенников виктор",
    "gender": "М",
    "hand": "R"
  },
  "68": {
    "name": "прончев антон",
    "gender": "М",
    "hand": "R"
  },
  "69": {
    "name": "верхова маргарита",
    "gender": "Ж",
    "hand": "R"
  },
  "70": {
    "name": "кумицкий владимир",
    "gender": "М",
    "hand": "R"
  },
  "71": {
    "name": "тен олег",
    "gender": "М",
    "hand": "R"
  },
  "72": {
    "name": "иевлева вероника",
    "gender": "Ж",
    "hand": "R"
  },
  "73": {
    "name": "иванов анатолий",
    "gender": "М",
    "hand": "R"
  },
  "74": {
    "name": "мельниченко михаил",
    "gender": "М",
    "hand": "L"
  },
  "75": {
    "name": "минеев евгений",
    "gender": "М",
    "hand": "R"
  },
  "76": {
    "name": "чекалкин андрей",
    "gender": "М",
    "hand": "L"
  },
  "77": {
    "name": "ильичев станислав",
    "gender": "М",
    "hand": "R"
  },
  "78": {
    "name": "альчаков андрей",
    "gender": "М",
    "hand": "R"
  },
  "79": {
    "name": "муравьев юрий",
    "gender": "М",
    "hand": "R"
  },
  "80": {
    "name": "андреев иван",
    "gender": "М",
    "hand": "R"
  },
  "81": {
    "name": "паршуков алексей",
    "gender": "М",
    "hand": "R"
  },
  "82": {
    "name": "шарипов азат",
    "gender": "М",
    "hand": "R"
  },
  "83": {
    "name": "суркова ольга",
    "gender": "Ж",
    "hand": "R"
  },
  "84": {
    "name": "опарин сергей",
    "gender": "М",
    "hand": "R"
  },
  "85": {
    "name": "королев юрий",
    "gender": "М",
    "hand": "R"
  },
  "86": {
    "name": "лесюк борис",
    "gender": "М",
    "hand": "R"
  },
  "87": {
    "name": "логинов константин",
    "gender": "М",
    "hand": "R"
  },
  "88": {
    "name": "васекина анастасия",
    "gender": "Ж",
    "hand": "R"
  },
  "89": {
    "name": "романова кира",
    "gender": "Ж",
    "hand": "R"
  },
  "90": {
    "name": "глазков юрий",
    "gender": "М",
    "hand": "R"
  },
  "91": {
    "name": "гончаров андрей",
    "gender": "М",
    "hand": "R"
  },
  "92": {
    "name": "майер максим",
    "gender": "М",
    "hand": "R"
  },
  "93": {
    "name": "агузарова людмила",
    "gender": "Ж",
    "hand": "R"
  },
  "94": {
    "name": "мандрица наталья",
    "gender": "Ж",
    "hand": "R"
  },
  "95": {
    "name": "резниченко александр",
    "gender": "М",
    "hand": "R"
  },
  "96": {
    "name": "жапаров даулет",
    "gender": "М",
    "hand": "R"
  },
  "97": {
    "name": "сизов юрий",
    "gender": "М",
    "hand": "R"
  },
  "98": {
    "name": "гадельшин артур",
    "gender": "М",
    "hand": "R"
  },
  "99": {
    "name": "захаров сергей",
    "gender": "М",
    "hand": "R"
  },
  "100": {
    "name": "мартынов сергей",
    "gender": "М",
    "hand": "R"
  },
  "101": {
    "name": "суханова галина",
    "gender": "Ж",
    "hand": "R"
  },
  "102": {
    "name": "гололобов алексей",
    "gender": "М",
    "hand": "R"
  },
  "103": {
    "name": "альчаков виктор",
    "gender": "М",
    "hand": "R"
  },
  "104": {
    "name": "шарипов тургунбек",
    "gender": "М",
    "hand": "R"
  },
  "105": {
    "name": "воронина екатерина",
    "gender": "Ж",
    "hand": "R"
  },
  "106": {
    "name": "кряжок дмитрий",
    "gender": "М",
    "hand": "R"
  },
  "107": {
    "name": "кошель мария",
    "gender": "Ж",
    "hand": "L"
  },
  "108": {
    "name": "сазонов иван",
    "gender": "М",
    "hand": "L"
  },
  "109": {
    "name": "дрожбин алексей",
    "gender": "М",
    "hand": "R"
  },
  "110": {
    "name": "еременко максим",
    "gender": "М",
    "hand": "R"
  },
  "111": {
    "name": "ландау максим",
    "gender": "М",
    "hand": "R"
  },
  "112": {
    "name": "муравьев иван",
    "gender": "М",
    "hand": "R"
  },
  "113": {
    "name": "белинский александр",
    "gender": "М",
    "hand": "R"
  },
  "114": {
    "name": "васекин александр",
    "gender": "М",
    "hand": "R"
  },
  "115": {
    "name": "зеленков антон",
    "gender": "М",
    "hand": "R"
  },
  "116": {
    "name": "глазков кирилл",
    "gender": "М",
    "hand": "R"
  },
  "117": {
    "name": "кряжок данил",
    "gender": "М",
    "hand": "R"
  },
  "118": {
    "name": "андреев сергей",
    "gender": "М",
    "hand": "R"
  },
  "119": {
    "name": "богачев сергей",
    "gender": "М",
    "hand": "R"
  },
  "120": {
    "name": "егорычев максим",
    "gender": "М",
    "hand": "L"
  },
  "121": {
    "name": "кобельков максим",
    "gender": "М",
    "hand": "R"
  },
  "122": {
    "name": "федоров федор",
    "gender": "М",
    "hand": "R"
  },
  "123": {
    "name": "арнаутов дмитрий",
    "gender": "М",
    "hand": "R"
  },
  "124": {
    "name": "зеленкова евгения",
    "gender": "Ж",
    "hand": "R"
  },
  "125": {
    "name": "щекачев вячеслав",
    "gender": "М",
    "hand": "R"
  },
  "126": {
    "name": "зубков артемий",
    "gender": "М",
    "hand": "R"
  },
  "127": {
    "name": "медведицков александр",
    "gender": "М",
    "hand": "R"
  },
  "128": {
    "name": "аржанов владислав",
    "gender": "М",
    "hand": "L"
  },
  "129": {
    "name": "недосеева дарья",
    "gender": "Ж",
    "hand": "R"
  },
  "130": {
    "name": "калинин константин",
    "gender": "М",
    "hand": "R"
  },
  "131": {
    "name": "беленький михаил",
    "gender": "М",
    "hand": "R"
  },
  "132": {
    "name": "егунов николай",
    "gender": "М",
    "hand": "R"
  },
  "133": {
    "name": "коршак ян",
    "gender": "М",
    "hand": "R"
  },
  "134": {
    "name": "соболев павел",
    "gender": "М",
    "hand": "R"
  },
  "135": {
    "name": "кононов александр",
    "gender": "М",
    "hand": "R"
  },
  "136": {
    "name": "апанякина ксения",
    "gender": "Ж",
    "hand": "R"
  },
  "137": {
    "name": "степаненко андрей",
    "gender": "М",
    "hand": "R"
  },
  "138": {
    "name": "григорьев владимир",
    "gender": "М",
    "hand": "R"
  },
  "139": {
    "name": "антропов александр",
    "gender": "М",
    "hand": "R"
  },
  "140": {
    "name": "кузнецов евгений",
    "gender": "М",
    "hand": "R"
  },
  "141": {
    "name": "панасенко максим",
    "gender": "М",
    "hand": "R"
  },
  "142": {
    "name": "плотников андрей",
    "gender": "М",
    "hand": "R"
  },
  "143": {
    "name": "кудрина полина",
    "gender": "Ж",
    "hand": "R"
  },
  "144": {
    "name": "мустафин артем",
    "gender": "М",
    "hand": "R"
  },
  "145": {
    "name": "говорин владислав",
    "gender": "М",
    "hand": "R"
  },
  "146": {
    "name": "бродюк иван",
    "gender": "М",
    "hand": "R"
  },
  "147": {
    "name": "родкин николай",
    "gender": "М",
    "hand": "R"
  },
  "148": {
    "name": "большаков даниил",
    "gender": "М",
    "hand": "R"
  },
  "149": {
    "name": "евдокимов сергей",
    "gender": "М",
    "hand": "R"
  },
  "150": {
    "name": "ярославцев алексей",
    "gender": "М",
    "hand": "R"
  },
  "151": {
    "name": "фоломин андрей",
    "gender": "М",
    "hand": "R"
  },
  "152": {
    "name": "хасанов искандер",
    "gender": "М",
    "hand": "R"
  },
  "153": {
    "name": "слабженников владимир",
    "gender": "М",
    "hand": "R"
  },
  "154": {
    "name": "четвертных денис",
    "gender": "М",
    "hand": "R"
  },
  "155": {
    "name": "шувалов александр",
    "gender": "М",
    "hand": "R"
  },
  "156": {
    "name": "байтулаева ажар",
    "gender": "Ж",
    "hand": "R"
  },
  "157": {
    "name": "торба людмила",
    "gender": "Ж",
    "hand": "R"
  },
  "158": {
    "name": "кусков виктор",
    "gender": "М",
    "hand": "R"
  },
  "159": {
    "name": "акопян арсен",
    "gender": "М",
    "hand": "R"
  },
  "160": {
    "name": "галин владимир",
    "gender": "М",
    "hand": "R"
  },
  "161": {
    "name": "горбунов виталий",
    "gender": "М",
    "hand": "R"
  },
  "162": {
    "name": "ополев александр",
    "gender": "М",
    "hand": "R"
  },
  "163": {
    "name": "савченко алексей",
    "gender": "М",
    "hand": "R"
  },
  "164": {
    "name": "потапов александр",
    "gender": "М",
    "hand": "R"
  },
  "165": {
    "name": "ополева анастасия",
    "gender": "Ж",
    "hand": "R"
  },
  "166": {
    "name": "покасова анастасия",
    "gender": "Ж",
    "hand": "R"
  },
  "167": {
    "name": "нигматуллин рустам",
    "gender": "М",
    "hand": "R"
  },
  "168": {
    "name": "лукманов ильшат",
    "gender": "М",
    "hand": "R"
  },
  "169": {
    "name": "кетов андрей",
    "gender": "М",
    "hand": "R"
  },
  "170": {
    "name": "ополев дмитрий",
    "gender": "М",
    "hand": "R"
  },
  "171": {
    "name": "паладий людмила",
    "gender": "Ж",
    "hand": "R"
  },
  "172": {
    "name": "туча оксана",
    "gender": "Ж",
    "hand": "R"
  },
  "173": {
    "name": "требухин сергей",
    "gender": "М",
    "hand": "R"
  },
  "174": {
    "name": "павленко андрей",
    "gender": "М",
    "hand": "R"
  },
  "175": {
    "name": "данилин дмитрий",
    "gender": "М",
    "hand": "R"
  },
  "176": {
    "name": "эккель жанна",
    "gender": "Ж",
    "hand": "R"
  },
  "177": {
    "name": "асылбеков тимур",
    "gender": "М",
    "hand": "R"
  },
  "178": {
    "name": "крыль игорь",
    "gender": "М",
    "hand": "R"
  },
  "179": {
    "name": "кононов александр - мл",
    "gender": "М",
    "hand": "R"
  },
  "180": {
    "name": "камалова нигара",
    "gender": "Ж",
    "hand": "R"
  },
  "181": {
    "name": "лозовая людмила",
    "gender": "Ж",
    "hand": "R"
  },
  "182": {
    "name": "сагатова гульчихра",
    "gender": "Ж",
    "hand": "R"
  },
  "183": {
    "name": "мартиросян атом",
    "gender": "М",
    "hand": "L"
  },
  "184": {
    "name": "таиров андрей",
    "gender": "М",
    "hand": "R"
  },
  "185": {
    "name": "кузнецов михаил",
    "gender": "М",
    "hand": "R"
  },
  "186": {
    "name": "дедов александр",
    "gender": "М",
    "hand": "R"
  },
  "187": {
    "name": "богданкевич станислав",
    "gender": "М",
    "hand": "R"
  },
  "188": {
    "name": "сагатов алишер",
    "gender": "М",
    "hand": "R"
  },
  "189": {
    "name": "белов андрей",
    "gender": "М",
    "hand": "R"
  },
  "190": {
    "name": "апасов александр",
    "gender": "М",
    "hand": "R"
  },
  "191": {
    "name": "магатаев александр",
    "gender": "М",
    "hand": "R"
  },
  "192": {
    "name": "суслов степан",
    "gender": "М",
    "hand": "R"
  },
  "193": {
    "name": "исмаилов азиз",
    "gender": "М",
    "hand": "R"
  },
  "194": {
    "name": "абдужабборов абдуррахим",
    "gender": "М",
    "hand": "R"
  },
  "195": {
    "name": "эгамбердиев зокир",
    "gender": "М",
    "hand": "R"
  },
  "196": {
    "name": "абдусамадов равшан",
    "gender": "М",
    "hand": "R"
  },
  "197": {
    "name": "разживин александр",
    "gender": "М",
    "hand": "R"
  },
  "198": {
    "name": "туйчиев даврон",
    "gender": "М",
    "hand": "L"
  },
  "199": {
    "name": "быстров валентин",
    "gender": "М",
    "hand": "R"
  },
  "200": {
    "name": "азизов бобур",
    "gender": "М",
    "hand": "R"
  },
  "201": {
    "name": "хилямов кудрат",
    "gender": "М",
    "hand": "R"
  },
  "202": {
    "name": "далабаев бахтиёр",
    "gender": "М",
    "hand": "R"
  },
  "203": {
    "name": "тохиров ойбек",
    "gender": "М",
    "hand": "R"
  },
  "204": {
    "name": "абдукаххаров зоир",
    "gender": "М",
    "hand": "R"
  },
  "205": {
    "name": "мухтаров олим",
    "gender": "М",
    "hand": "R"
  },
  "206": {
    "name": "якубов уткир",
    "gender": "М",
    "hand": "R"
  },
  "207": {
    "name": "лефтер татьяна",
    "gender": "Ж",
    "hand": "R"
  },
  "208": {
    "name": "арифов баходир",
    "gender": "М",
    "hand": "R"
  },
  "209": {
    "name": "шипилов илья",
    "gender": "М",
    "hand": "R"
  },
  "210": {
    "name": "каримов феруз",
    "gender": "М",
    "hand": "R"
  },
  "211": {
    "name": "сагатов санджар",
    "gender": "М",
    "hand": "R"
  },
  "212": {
    "name": "каримов хабибулло",
    "gender": "М",
    "hand": "R"
  },
  "213": {
    "name": "криворотов виктор",
    "gender": "М",
    "hand": "R"
  },
  "214": {
    "name": "сафаров азамат",
    "gender": "М",
    "hand": "R"
  },
  "215": {
    "name": "криворотова эллана",
    "gender": "Ж",
    "hand": "L"
  },
  "216": {
    "name": "комилов иззатилла",
    "gender": "М",
    "hand": "R"
  },
  "217": {
    "name": "нормухамедов омил",
    "gender": "М",
    "hand": "R"
  },
  "218": {
    "name": "рахматов аъзамхон",
    "gender": "М",
    "hand": "R"
  },
  "219": {
    "name": "аубекерова айгуль",
    "gender": "Ж",
    "hand": "R"
  },
  "220": {
    "name": "баракатова шолпан",
    "gender": "Ж",
    "hand": "R"
  },
  "221": {
    "name": "саидхаджаев сардор",
    "gender": "М",
    "hand": "R"
  },
  "222": {
    "name": "кунц инна",
    "gender": "Ж",
    "hand": "R"
  },
  "223": {
    "name": "егембердиев алмас",
    "gender": "М",
    "hand": "R"
  },
  "224": {
    "name": "сагатов сардорбек",
    "gender": "М",
    "hand": "R"
  },
  "225": {
    "name": "магда виктор",
    "gender": "М",
    "hand": "R"
  },
  "226": {
    "name": "галаев эдуард",
    "gender": "М",
    "hand": "R"
  },
  "227": {
    "name": "мурадян хачатур",
    "gender": "М",
    "hand": "L"
  },
  "228": {
    "name": "галаев владимир",
    "gender": "М",
    "hand": "R"
  },
  "229": {
    "name": "шахардинов алексей",
    "gender": "М",
    "hand": "R"
  },
  "230": {
    "name": "соленова надежда",
    "gender": "Ж",
    "hand": "R"
  },
  "231": {
    "name": "перфилов александр",
    "gender": "М",
    "hand": "R"
  },
  "232": {
    "name": "соколов максим",
    "gender": "М",
    "hand": "R"
  },
  "233": {
    "name": "матюшок владислав",
    "gender": "М",
    "hand": "R"
  },
  "234": {
    "name": "бойко ростислав",
    "gender": "М",
    "hand": "R"
  },
  "235": {
    "name": "королева лилия",
    "gender": "Ж",
    "hand": "R"
  },
  "236": {
    "name": "белинский сергей",
    "gender": "М",
    "hand": "R"
  },
  "237": {
    "name": "урчуков альберт",
    "gender": "М",
    "hand": "R"
  },
  "238": {
    "name": "алымов сергей",
    "gender": "М",
    "hand": "R"
  },
  "239": {
    "name": "носенко денис",
    "gender": "М",
    "hand": "R"
  },
  "240": {
    "name": "сусликова елена",
    "gender": "Ж",
    "hand": "R"
  },
  "241": {
    "name": "судат максим",
    "gender": "М",
    "hand": "R"
  },
  "242": {
    "name": "тинякова елена",
    "gender": "Ж",
    "hand": "R"
  },
  "243": {
    "name": "пименов вадим",
    "gender": "М",
    "hand": "R"
  },
  "244": {
    "name": "максимов артем",
    "gender": "М",
    "hand": "R"
  },
  "245": {
    "name": "окороков максим",
    "gender": "М",
    "hand": "R"
  },
  "246": {
    "name": "прохан сергей",
    "gender": "М",
    "hand": "R"
  },
  "247": {
    "name": "мохирева юлия",
    "gender": "Ж",
    "hand": "R"
  },
  "248": {
    "name": "сулейманян арамаис",
    "gender": "М",
    "hand": "R"
  },
  "249": {
    "name": "коробко алексей",
    "gender": "М",
    "hand": "R"
  },
  "250": {
    "name": "редько евгений",
    "gender": "М",
    "hand": "R"
  },
  "251": {
    "name": "фурашкин сергей",
    "gender": "М",
    "hand": "R"
  },
  "252": {
    "name": "кряжок светлана",
    "gender": "Ж",
    "hand": "R"
  },
  "253": {
    "name": "семенов иван",
    "gender": "М",
    "hand": "R"
  },
  "254": {
    "name": "устинов михаил",
    "gender": "М",
    "hand": "R"
  },
  "255": {
    "name": "поторочин владимир",
    "gender": "М",
    "hand": "R"
  },
  "256": {
    "name": "кузнецов дмитрий",
    "gender": "М",
    "hand": "R"
  },
  "257": {
    "name": "кравченко марина",
    "gender": "Ж",
    "hand": "R"
  },
  "258": {
    "name": "макаров антон",
    "gender": "М",
    "hand": "R"
  },
  "259": {
    "name": "шарапова алена",
    "gender": "Ж",
    "hand": "R"
  },
  "260": {
    "name": "овчинников олег",
    "gender": "М",
    "hand": "R"
  },
  "261": {
    "name": "полонский дмитрий",
    "gender": "М",
    "hand": "R"
  },
  "262": {
    "name": "фисин дмитрий",
    "gender": "М",
    "hand": "R"
  },
  "263": {
    "name": "кряжок владимир",
    "gender": "М",
    "hand": "R"
  },
  "264": {
    "name": "гаврилов степан",
    "gender": "М",
    "hand": "R"
  },
  "265": {
    "name": "обухов александр",
    "gender": "М",
    "hand": "R"
  },
  "266": {
    "name": "иванов антон",
    "gender": "М",
    "hand": "R"
  },
  "267": {
    "name": "гришененко елена",
    "gender": "Ж",
    "hand": "R"
  },
  "268": {
    "name": "абинаев абдрахман",
    "gender": "М",
    "hand": "R"
  },
  "269": {
    "name": "ахраров равшан",
    "gender": "М",
    "hand": "R"
  },
  "270": {
    "name": "саипов фархад",
    "gender": "М",
    "hand": "R"
  },
  "271": {
    "name": "фадеева анна",
    "gender": "Ж",
    "hand": "R"
  },
  "272": {
    "name": "зюзина елена",
    "gender": "Ж",
    "hand": "R"
  },
  "273": {
    "name": "абдухапаров мирзахмат",
    "gender": "М",
    "hand": "R"
  },
  "274": {
    "name": "ефремов александр",
    "gender": "М",
    "hand": "R"
  },
  "275": {
    "name": "кузнецова яна",
    "gender": "Ж",
    "hand": "R"
  },
  "276": {
    "name": "сафиуллин артем",
    "gender": "М",
    "hand": "R"
  },
  "277": {
    "name": "наседкин денис",
    "gender": "М",
    "hand": "R"
  },
  "278": {
    "name": "ким александр",
    "gender": "М",
    "hand": "R"
  },
  "279": {
    "name": "распутин андрей",
    "gender": "М",
    "hand": "R"
  },
  "280": {
    "name": "колтышев юрий",
    "gender": "М",
    "hand": "R"
  },
  "281": {
    "name": "трофимов михаил",
    "gender": "М",
    "hand": "R"
  },
  "282": {
    "name": "кудымов сергей",
    "gender": "М",
    "hand": "R"
  },
  "283": {
    "name": "солощенко петр",
    "gender": "М",
    "hand": "R"
  },
  "284": {
    "name": "шубырева мария",
    "gender": "Ж",
    "hand": "R"
  },
  "285": {
    "name": "кафлевская анна",
    "gender": "Ж",
    "hand": "R"
  },
  "286": {
    "name": "перепелкина ольга",
    "gender": "Ж",
    "hand": "R"
  },
  "287": {
    "name": "иванова валентина",
    "gender": "Ж",
    "hand": "R"
  },
  "288": {
    "name": "крисанова анна",
    "gender": "Ж",
    "hand": "R"
  },
  "289": {
    "name": "беляев михаил",
    "gender": "М",
    "hand": "R"
  },
  "290": {
    "name": "сазонов олег",
    "gender": "М",
    "hand": "R"
  },
  "291": {
    "name": "листопадова татьяна",
    "gender": "Ж",
    "hand": "R"
  },
  "292": {
    "name": "миронов андрей",
    "gender": "М",
    "hand": "R"
  },
  "293": {
    "name": "шин джонг хен",
    "gender": "М",
    "hand": "R"
  },
  "294": {
    "name": "ташимов галымжан",
    "gender": "М",
    "hand": "R"
  },
  "295": {
    "name": "кораблинова надежда",
    "gender": "Ж",
    "hand": "R"
  },
  "296": {
    "name": "сабыров баубек",
    "gender": "М",
    "hand": "R"
  },
  "297": {
    "name": "болтаев лазиз",
    "gender": "М",
    "hand": "R"
  },
  "298": {
    "name": "аниховский анатолий",
    "gender": "М",
    "hand": "R"
  },
  "299": {
    "name": "дорош ольга",
    "gender": "Ж",
    "hand": "R"
  },
  "300": {
    "name": "усманов дастанбек",
    "gender": "М",
    "hand": "R"
  },
  "301": {
    "name": "кондратенко игорь",
    "gender": "М",
    "hand": "R"
  },
  "302": {
    "name": "альчакова наталья",
    "gender": "Ж",
    "hand": "R"
  },
  "303": {
    "name": "грязин евгений",
    "gender": "М",
    "hand": "R"
  },
  "304": {
    "name": "кропачев евгений",
    "gender": "М",
    "hand": "R"
  },
  "305": {
    "name": "дьяков александр",
    "gender": "М",
    "hand": "R"
  },
  "306": {
    "name": "еремкин илья",
    "gender": "М",
    "hand": "R"
  },
  "307": {
    "name": "сутовский герман",
    "gender": "М",
    "hand": "R"
  },
  "308": {
    "name": "безруков евгений",
    "gender": "М",
    "hand": "R"
  },
  "309": {
    "name": "гадельшин тимур",
    "gender": "М",
    "hand": "R"
  },
  "310": {
    "name": "романюк дмитрий",
    "gender": "М",
    "hand": "R"
  },
  "311": {
    "name": "габдрахманов радик",
    "gender": "М",
    "hand": "R"
  },
  "313": {
    "name": "рошонок алла",
    "gender": "Ж",
    "hand": "R"
  },
  "314": {
    "name": "болдин роман",
    "gender": "М",
    "hand": "R"
  },
  "316": {
    "name": "куликова ксения",
    "gender": "Ж",
    "hand": "R"
  },
  "317": {
    "name": "иванов василий",
    "gender": "М",
    "hand": "R"
  },
  "318": {
    "name": "ашуров мехроб",
    "gender": "М",
    "hand": "R"
  },
  "319": {
    "name": "васильев андрей",
    "gender": "М",
    "hand": "R"
  },
  "320": {
    "name": "рупасов евгений",
    "gender": "М",
    "hand": "R"
  },
  "321": {
    "name": "чехлатый александр",
    "gender": "М",
    "hand": "R"
  }
}